flowagents/__init__.py
flowagents/base_agent.py
flowagents/fields.py
flowagents/message.py
flowagents/protocols.py
flowagents/py.typed
flowagents/result.py
flowagents/standard_agent.py
flowagents/agents/__init__.py
flowagents/agents/decorator.py
flowagents/agents/discovery.py
flowagents/checkpoint/__init__.py
flowagents/checkpoint/manager.py
flowagents/checkpoint/models.py
flowagents/checkpoint/storage.py
flowagents/config/__init__.py
flowagents/config/loader.py
flowagents/config/registry.py
flowagents/formatter/__init__.py
flowagents/formatter/base.py
flowagents/formatter/formatters.py
flowagents/formatter/models.py
flowagents/group/__init__.py
flowagents/group/group.py
flowagents/group/map_reduce.py
flowagents/group/merge.py
flowagents/group/models.py
flowagents/hooks/__init__.py
flowagents/hooks/decorators.py
flowagents/hooks/handlers.py
flowagents/hooks/manager.py
flowagents/hooks/models.py
flowagents/llm/__init__.py
flowagents/llm/anthropic_client.py
flowagents/llm/azure_client.py
flowagents/llm/base.py
flowagents/llm/dashscope_client.py
flowagents/llm/gemini_client.py
flowagents/llm/ollama_client.py
flowagents/llm/openai_client.py
flowagents/llm/registry.py
flowagents/mcp/__init__.py
flowagents/mcp/client.py
flowagents/mcp/models.py
flowagents/mcp/protocol.py
flowagents/mcp/provider.py
flowagents/memory/__init__.py
flowagents/memory/manager.py
flowagents/memory/models.py
flowagents/msghub/__init__.py
flowagents/msghub/hub.py
flowagents/msghub/models.py
flowagents/orchestrator/__init__.py
flowagents/orchestrator/models.py
flowagents/orchestrator/orchestrator.py
flowagents/orchestrator/pool.py
flowagents/orchestrator/router.py
flowagents/streaming/__init__.py
flowagents/streaming/engine.py
flowagents/streaming/models.py
flowagents/tools/__init__.py
flowagents/tools/decorator.py
flowagents/tools/executor.py
flowagents/tools/models.py
flowagents/tools/registry.py
flowagents/workflow/__init__.py
flowagents/workflow/executor.py
flowagents/workflow/loader.py
flowagents-0.1.1.dist-info/METADATA
flowagents-0.1.1.dist-info/WHEEL
flowagents-0.1.1.dist-info/licenses/LICENSE
flowagents-0.1.1.dist-info/RECORD
