Metadata-Version: 2.4
Name: flowagents
Version: 0.1.1
Summary: A zero-code AI workflow orchestration framework with state-driven agents
Project-URL: Homepage, https://github.com/xiaoyu-work/flowagents
Project-URL: Documentation, https://xiaoyu-work.github.io/flowagents
Project-URL: Repository, https://github.com/xiaoyu-work/flowagents
Project-URL: Issues, https://github.com/xiaoyu-work/flowagents/issues
Author: FlowAgents Contributors
License-Expression: MIT
License-File: LICENSE
Keywords: agent,ai,anthropic,claude,framework,gpt,llm,multi-agent,openai,orchestration,state-machine,streaming,workflow,yaml,zero-code
Classifier: Development Status :: 4 - Beta
Classifier: Intended Audience :: Developers
Classifier: License :: OSI Approved :: MIT License
Classifier: Programming Language :: Python :: 3
Classifier: Programming Language :: Python :: 3.9
Classifier: Programming Language :: Python :: 3.10
Classifier: Programming Language :: Python :: 3.11
Classifier: Programming Language :: Python :: 3.12
Classifier: Topic :: Scientific/Engineering :: Artificial Intelligence
Classifier: Topic :: Software Development :: Libraries :: Python Modules
Classifier: Typing :: Typed
Requires-Python: >=3.9
Requires-Dist: pydantic>=2.0
Requires-Dist: pyyaml>=6.0
Provides-Extra: all
Requires-Dist: aiosqlite>=0.19; extra == 'all'
Requires-Dist: anthropic>=0.18; extra == 'all'
Requires-Dist: dashscope>=1.14; extra == 'all'
Requires-Dist: google-generativeai>=0.3; extra == 'all'
Requires-Dist: httpx>=0.25; extra == 'all'
Requires-Dist: mcp>=0.9; extra == 'all'
Requires-Dist: openai>=1.0; extra == 'all'
Provides-Extra: anthropic
Requires-Dist: anthropic>=0.18; extra == 'anthropic'
Provides-Extra: dashscope
Requires-Dist: dashscope>=1.14; extra == 'dashscope'
Provides-Extra: gemini
Requires-Dist: google-generativeai>=0.3; extra == 'gemini'
Provides-Extra: mcp
Requires-Dist: mcp>=0.9; extra == 'mcp'
Provides-Extra: ollama
Requires-Dist: httpx>=0.25; extra == 'ollama'
Provides-Extra: openai
Requires-Dist: openai>=1.0; extra == 'openai'
